gcpds/docs/__init__.py
gcpds/docs/workflows/automated-setup.yml
gcpds/docs/workflows/automated-sphinx-docs.yml
gcpds_docs-0.5.dist-info/LICENSE
gcpds_docs-0.5.dist-info/METADATA
gcpds_docs-0.5.dist-info/WHEEL
gcpds_docs-0.5.dist-info/top_level.txt
gcpds_docs-0.5.dist-info/RECORD
