Metadata-Version: 2.1
Name: gcpds-docs
Version: 0.5
Download-URL: 
Author: Yeison Cardona
Author-email: yencardonaal@unal.edu.co
Maintainer: Yeison Cardona
Maintainer-email: yencardonaal@unal.edu.co
License: Simplified BSD License
Requires-Python: >=3.7
License-File: LICENSE
Requires-Dist: ipywidgets
Requires-Dist: ipython-secrets
